{
  "project_info": {
    "project_number": "616930047652",
    "project_id": "fpshare2",
    "storage_bucket": "fpshare2.appspot.com"
  },
  "client": [
    {
      "client_info": {
        "mobilesdk_app_id": "1:616930047652:android:c454668c7f7487d0abd831",
        "android_client_info": {
          "package_name": "com.albert.fpshare"
        }
      },
      "oauth_client": [],
      "api_key": [
        {
          "current_key": "AIzaSyAeIP62SPDzPGFWDPghZmfLsP-OYJzeFg8"
        }
      ],
      "services": {
        "appinvite_service": {
          "other_platform_oauth_client": []
        }
      }
    }
  ],
  "configuration_version": "1"
}